{
	"id": "f9337051-243e-458f-a073-42583e4865af",
	"name": "local",
	"values": [
		{
			"key": "url",
			"value": "http://localhost:3000",
			"type": "default",
			"enabled": true
		},
		{
			"key": "health_url",
			"value": "http://localhost:3001",
			"type": "default",
			"enabled": true
		},
		{
			"key": "access_token",
			"value": "",
			"type": "default",
			"enabled": true
		},
		{
			"key": "companyID",
			"value": "",
			"type": "default",
			"enabled": true
		}
	],
	"_postman_variable_scope": "environment",
	"_postman_exported_at": "2024-12-05T15:29:35.714Z",
	"_postman_exported_using": "Postman/11.21.0"
}